Workbook
Name Product: index_match!$E$2:$E$1048576
Name Product_Category: index_match!$B$2:$B$1048576
Name Product_TypeA: index_match!$A$2:$A$1048576
Name Profit: index_match!$C$2:$C$1048576
Name Sales: index_match!$D$2:$D$1048576
Name superstore_data: Sheet1!$A$2:$D$103

Sheet producttype_info
A1: Product | B1: Product Type
A2: Amaretto | B2: Coffee
A3: Caffe Latte | B3: Espresso
A4: Caffe Mocha | B4: Espresso
A5: Chamomile | B5: Herbal Tea
A6: Colombian | B6: Coffee
A7: Darjeeling | B7: Tea
A8: Decaf Espresso | B8: Espresso
A9: Decaf Irish Cream | B9: Coffee
A10: Earl Grey | B10: Tea
A11: Green Tea | B11: Tea
A12: Lemon | B12: Herbal Tea
... A14: Regular Espresso | B14: Espresso

Sheet lookup_data
A1: Area Code | B1: Product | C1: Product Type | D1: State | E1: Territory | F1: Target Profit | G1: Profit | H1: Marked Price
A2: 970 | B2: Decaf Irish Cream | C2: =VLOOKUP(B2,producttype_info!$A$1:$B$14,2,FALSE) -> Coffee | D2: Colorado | E2: Central | F2: 110 | G2: 101 | H2: 234
A3: 309 | B3: Decaf Irish Cream | C3: =VLOOKUP(B3,producttype_info!$A$1:$B$14,2,FALSE) -> Coffee | D3: Illinois | E3: Central | F3: 100 | G3: 87 | H3: 234
A4: 614 | B4: Decaf Irish Cream | C4: =VLOOKUP(B4,producttype_info!$A$1:$B$14,2,FALSE) -> Coffee | D4: Ohio | E4: Central | F4: 20 | G4: 0 | H4: 150
A5: 754 | B5: Decaf Irish Cream | C5: =VLOOKUP(B5,producttype_info!$A$1:$B$14,2,FALSE) -> Coffee | D5: Florida | E5: East | F5: 70 | G5: 67 | H5: 200
A6: 325 | B6: Decaf Irish Cream | C6: =VLOOKUP(B6,producttype_info!$A$1:$B$14,2,FALSE) -> Coffee | D6: Texas | E6: South | F6: 100 | G6: 68 | H6: 190
A7: 650 | B7: Decaf Irish Cream | C7: =VLOOKUP(B7,producttype_info!$A$1:$B$14,2,FALSE) -> Coffee | D7: California | E7: West | F7: 120 | G7: 117 | H7: 118
A8: 720 | B8: Decaf Espresso | C8: =VLOOKUP(B8,producttype_info!$A$1:$B$14,2,FALSE) -> Espresso | D8: Colorado | E8: Central | F8: 80 | G8: 53 | H8: 180
A9: 630 | B9: Decaf Espresso | C9: =VLOOKUP(B9,producttype_info!$A$1:$B$14,2,FALSE) -> Espresso | D9: Illinois | E9: Central | F9: 180 | G9: 140 | H9: 456
A10: 614 | B10: Decaf Espresso | C10: =VLOOKUP(B10,producttype_info!$A$1:$B$14,2,FALSE) -> Espresso | D10: Ohio | E10: Central | F10: 40 | G10: 16 | H10: 130
A11: 754 | B11: Decaf Espresso | C11: =VLOOKUP(B11,producttype_info!$A$1:$B$14,2,FALSE) -> Espresso | D11: Florida | E11: East | F11: 60 | G11: 50 | H11: 180
A12: 956 | B12: Decaf Espresso | C12: =VLOOKUP(B12,producttype_info!$A$1:$B$14,2,FALSE) -> Espresso | D12: Texas | E12: South | F12: 60 | G12: 54 | H12: 134
A13: 213 | B13: Decaf Espresso | C13: =VLOOKUP(B13,producttype_info!$A$1:$B$14,2,FALSE) -> Espresso | D13: California | E13: West | F13: 200 | G13: 203 | H13: 546
... A101: 970 | B101: Mint | C101: =VLOOKUP(B101,producttype_info!$A$1:$B$14,2,FALSE) -> Herbal Tea | D101: Colorado | E101: Central | F101: 40 | G101: 33 | H101: 140

Sheet Sheet1
A1: Order ID | B1: Customer Name | C1: Profit | D1: Sales
A2: CA-2019-100867 | B2: Eugene Hildebrand | C2: 9 | D2: 33
A3: CA-2019-107153 | B3: George Zrebassa | C3: 4 | D3: 11
A4: CA-2019-115238 | B4: Jane Waco | C4: 89 | D4: 281
A5: CA-2019-115777 | B5: Doug O'Connell | C5: 182 | D5: 388
A6: CA-2019-117964 | B6: Michael Knudson | C6: -19 | D6: 56
A7: CA-2019-119508 | B7: Tracy Zic | C7: 15 | D7: 42
A8: CA-2019-123625 | B8: Bruce Galang | C8: 88 | D8: 258
A9: CA-2019-123664 | B9: Neil Cohen | C9: -25 | D9: 58
A10: CA-2019-125388 | B10: Michael Paige | C10: 26 | D10: 174
A11: CA-2019-126438 | B11: Alex Russell | C11: 4 | D11: 15
A12: CA-2019-126634 | B12: Alan Barnes | C12: 40 | D12: 94 | H12: Order ID | I12: Customer Name | J12: Profit | K12: Sales
A13: CA-2019-129322 | B13: Denny Blanton | C13: 255 | D13: 601 | H13: CA-2019-123664 | I13: =I19 -> 0
A14: CA-2019-131807 | B14: Greg Guthrie | C14: -14 | D14: 753 | F14: =MATCH(B1,A1:D1,0) -> 2
A15: CA-2019-132339 | B15: Jennifer Braxton | C15: 9 | D15: 19 | F15: =MATCH("Sales",A1:D1) -> 4
A16: CA-2019-139675 | B16: Nicole Fjeld | C16: 195 | D16: 1243
A17: CA-2019-141531 | B17: Bruce Galang | C17: 30 | D17: 88
A18: CA-2019-143500 | B18: Harry Olson | C18: -1 | D18: 3
A19: CA-2019-146626 | B19: James Peterman | C19: 10 | D19: 20
A20: CA-2019-151799 | B20: Ben Ferrer | C20: 432 | D20: 1843
A21: CA-2019-152443 | B21: Frank Gastineau | C21: 297 | D21: 712
A22: CA-2019-153623 | B22: James Peterman | C22: 71 | D22: 198
A23: CA-2019-153738 | B23: Alejandro Grove | C23: 17 | D23: 38
A24: CA-2019-160325 | B24: Bart Pistole | C24: 241 | D24: 830
A25: CA-2019-166086 | B25: Carol Triggs | C25: 216 | D25: 1091
A26: CA-2019-166695 | B26: Chuck Clark | C26: -55 | D26: 868
A27: CA-2019-184712 | B27: Neil Cohen | C27: 23 | D27: 74
... A104: CA-2020-111111 | B104: Karthick | C104: 8 | D104: 18

Sheet xlookup
A1: Product | B1: Quarter1 | C1: Quarter 2 | D1: Quarter3
A2: Regular Expresso | B2: $ 1,234 | C2: $ 731 | D2: $ 5,678
A3: Mint | B3: $ 8,976 | C3: $ 8,765 | D3: $ 6,709 | G3: Product | H3: Quarter
A4: Lemon | B4: $ 4,567 | C4: $ 4,367 | D4: $ 7,509 | G4: Decaf Irish Cream | H4: Quarter1
A5: Green Tea | B5: $ 7,896 | C5: $ 9,823 | D5: $ 3,456
A6: Earl Grey | B6: $ 4,567 | C6: $ 4,587 | D6: $ 7,623 | H6: =INDEX(B2:D14,MATCH(G4,A2:A14,0),MATCH(H4,B1:D1,0)) -> $ 6,543
A7: Decaf Irish Cream | B7: $ 6,543 | C7: $ 2,458 | D7: $ 1,348 | H7: =INDEX(twoway_table[[Quarter1]:[Quarter3]],MATCH(G4,twoway_table[Product],0),MATCH(H4,twoway_table[[#Headers],[Quarter1]:[Quarter3]],0)) -> $ 6,543
A8: Decaf Expresso | B8: $ 3,679 | C8: $ 9,875 | D8: $ 9,876
A9: Darjelling | B9: $ 8,734 | C9: $ 3,568 | D9: $ 5,634
A10: Colombian | B10: $ 2,567 | C10: $ 9,865 | D10: $ 5,687
A11: Chamomile | B11: $ 8,632 | C11: $ 4,689 | D11: $ 6,534
A12: Caffe Mocha | B12: $ 6,790 | C12: $ 278 | D12: $ 2,578
A13: Caffe Latte | B13: $ 5,320 | C13: $ 1,789 | D13: $ 6,543
A14: Amaretto | B14: $ 7,801 | C14: $ 9,845 | D14: $ 8,765

Sheet index_match
A1: Product TypeA | B1: Product Category | C1: Profit | D1: Sales | E1: Product | K1: Product | L1: Café Mocha
A2: Coffee | B2: Beans | C2: $4,786 | D2: $11,457 | E2: Amaratto | K2: Product Category | L2: =INDEX(B2:B17,MATCH(L1,E2:E17)) -> Beans
A3: Expresso | B3: Beans | C3: $8,765 | D3: $78,965 | E3: cafelatte | K3: Product Type
A4: Herbal Tea | B4: Leaves | C4: $ 4,568 | D4: $9,876 | E4: Lemon | K4: Profit
A5: Tea | B5: Leaves | C5: $ 9,875 | D5: $12,456 | E5: Mint | K5: Sales
A6: Coffee | B6: Beans | C6: $ 3,456 | D6: $9,876 | E6: Café Mocha
A7: Expresso | B7: Beans | C7: $ 987 | D7: $4,578 | E7: Regualar Expresso
A8: Herbal Tea | B8: Leaves | C8: $ 6,784 | D8: $87,543 | E8: Lemon ice
A9: Tea | B9: Leaves | C9: $ 2,398 | D9: $4,567 | E9: Lemon cool
A10: Coffee | B10: Beans | C10: $ 45,098 | D10: $11,267 | E10: Decaf Irish Cream
A11: Expresso | B11: Beans | C11: $ 3,489 | D11: $8,905 | E11: Clombian
A12: Herbal Tea | B12: Leaves | C12: $ 6,709 | D12: $7,890 | E12: Mint bar | K12: Product | L12: Lemon
A13: Tea | B13: Leaves | C13: $ 2,319 | D13: $4,590 | E13: Regular Lemon | K13: Product Category | L13: =INDEX(Product_Category,MATCH(L12,Product)) -> Leaves
A14: Coffee | B14: Beans | C14: $ 78,965 | D14: $118,796 | E14: cafelatte | K14: Product Type | L14: =INDEX(im_table[Product TypeA],MATCH(L12,im_table[Product],0)) -> Herbal Tea
A15: Expresso | B15: Beans | C15: $ 9,843 | D15: $98,765 | E15: Regualar Expresso | K15: Profit
A16: Herbal Tea | B16: Leaves | C16: $ 8,765 | D16: $95,438 | E16: Lemon Sparsh | K16: Sales
A17: Tea | B17: Leaves | C17: $ 7,895 | D17: $123,679 | E17: Mint

Sheet hlookup
A1: Order ID | B1: CA-2019-100867 | C1: CA-2019-107153 | D1: CA-2019-115238 | E1: CA-2019-115777 | F1: CA-2019-117964 | G1: CA-2019-119508 | H1: CA-2019-123625 | I1: CA-2019-123664 | J1: CA-2019-125388 | K1: CA-2019-126438 | L1: CA-2019-126634 | M1: CA-2019-129322 | N1: CA-2019-131807 | O1: CA-2019-132339 | P1: CA-2019-139675 | Q1: CA-2019-141531 | R1: CA-2019-143500 | S1: CA-2019-146626 | T1: CA-2019-151799 | U1: CA-2019-152443 | V1: CA-2019-153623 | W1: CA-2019-153738 | X1: CA-2019-160325 | Y1: CA-2019-166086 | Z1: CA-2019-166695 | AA1: CA-2019-184712 | AB1: CA-2020-112224 | AC1: CA-2020-115238 | AD1: CA-2020-119508 | AE1: CA-2020-129322 | AF1: CA-2020-132548 | AG1: CA-2020-139675 | AH1: CA-2020-145154 | AI1: CA-2020-150547 | AJ1: CA-2020-152681 | AK1: CA-2020-153071 | AL1: CA-2020-153738 | AM1: CA-2020-154124 | AN1: CA-2020-154231 | AO1: CA-2020-155586 | AP1: CA-2020-158792 | AQ1: CA-2021-108735 | AR1: CA-2021-111254 | AS1: CA-2021-112109 | AT1: CA-2021-115238 | AU1: CA-2021-115483 | AV1: CA-2021-119508 | AW1: CA-2021-121465 | AX1: CA-2021-124574 | AY1: CA-2021-124626 | AZ1: CA-2021-125724 | BA1: CA-2021-126627 | BB1: CA-2021-129322 | BC1: CA-2021-133541 | BD1: CA-2021-135480 | BE1: CA-2021-136547 | BF1: CA-2021-139675 | BG1: CA-2021-141082 | BH1: CA-2021-153738 | BI1: CA-2021-155412 | BJ1: CA-2021-155586 | BK1: CA-2021-158792 | BL1: CA-2021-169856 | BM1: CA-2021-174514 | BN1: CA-2021-187423 | BO1: CA-2021-192314 | BP1: CA-2022-105471 | BQ1: CA-2022-106541 | BR1: CA-2022-107004 | BS1: CA-2022-108735 | BT1: CA-2022-112109 | BU1: CA-2022-115238 | BV1: CA-2022-115483 | BW1: CA-2022-115777 | BX1: CA-2022-119508 | BY1: CA-2022-121451 | BZ1: CA-2022-124626 | CA1: CA-2022-125388 | CB1: CA-2022-125724 | CC1: CA-2022-126438 | CD1: CA-2022-126627 | CE1: CA-2022-126634 | CF1: CA-2022-129322 | CG1: CA-2022-130494 | CH1: CA-2022-131807 | CI1: CA-2022-132339 | CJ1: CA-2022-135471 | CK1: CA-2022-135480 | CL1: CA-2022-139675 | CM1: CA-2022-141082 | CN1: CA-2022-141531 | CO1: CA-2022-143500 | CP1: CA-2022-145612 | CQ1: CA-2022-146626 | CR1: CA-2022-151799 | CS1: CA-2022-153738 | CT1: CA-2022-154121 | CU1: CA-2022-158740 | CV1: CA-2022-160325 | CW1: CA-2022-166695 | CX1: CA-2022-184712 | CY1: CA-2022-192314 | CZ1: CA-2020-111111
A2: Customer Name | B2: Eugene Hildebrand | C2: George Zrebassa | D2: Jane Waco | E2: Doug O'Connell | F2: Michael Knudson | G2: Tracy Zic | H2: Bruce Galang | I2: Neil Cohen | J2: Michael Paige | K2: Alex Russell | L2: Alan Barnes | M2: Denny Blanton | N2: Greg Guthrie | O2: Jennifer Braxton | P2: Nicole Fjeld | Q2: Bruce Galang | R2: Harry Olson | S2: James Peterman | T2: Ben Ferrer | U2: Frank Gastineau | V2: James Peterman | W2: Alejandro Grove | X2: Bart Pistole | Y2: Carol Triggs | Z2: Chuck Clark | AA2: Neil Cohen | AB2: Neil Cohen | AC2: Jane Waco | AD2: Tracy Zic | AE2: Denny Blanton | AF2: Carol Triggs | AG2: Nicole Fjeld | AH2: Michael Knudson | AI2: Frank Gastineau | AJ2: Scott Cohen | AK2: George Zrebassa | AL2: Alejandro Grove | AM2: Michael Knudson | AN2: Eugene Hildebrand | AO2: Xylona Preis | AP2: Brian Dahlen | AQ2: Jessica Myrick | AR2: Michael Knudson | AS2: Joe Elijah | AT2: Jane Waco | AU2: Jill Trafton | AV2: Tracy Zic | AW2: Harry Olson | AX2: Michael Knudson | AY2: James Peterman | AZ2: Suzanne McNair | BA2: William Brown | BB2: Denny Blanton | BC2: Neil Cohen | BD2: Bruce Galang | BE2: Frank Gastineau | BF2: Nicole Fjeld | BG2: Fred McMath | BH2: Alejandro Grove | BI2: Scott Cohen | BJ2: Xylona Preis | BK2: Brian Dahlen | BL2: Carol Triggs | BM2: Eugene Hildebrand | BN2: George Zrebassa | BO2: Jennifer Sheldon | BP2: Neil Cohen | BQ2: Michael Knudson | BR2: Eugene Hildebrand | BS2: Jessica Myrick | BT2: Joe Elijah | BU2: Jane Waco | BV2: Jill Trafton | BW2: Doug O'Connell | BX2: Tracy Zic | BY2: Scott Cohen | BZ2: James Peterman | CA2: Michael Paige | CB2: Suzanne McNair | CC2: Alex Russell | CD2: William Brown | CE2: Alan Barnes | CF2: Denny Blanton | CG2: Harry Olson | CH2: Greg Guthrie | CI2: Jennifer Braxton | CJ2: George Zrebassa | CK2: Bruce Galang | CL2: Nicole Fjeld | CM2: Fred McMath | CN2: Bruce Galang | CO2: Harry Olson | CP2: Michael Knudson | CQ2: James Peterman | CR2: Ben Ferrer | CS2: Alejandro Grove | CT2: Scott Cohen | CU2: Frank Gastineau | CV2: Bart Pistole | CW2: Chuck Clark | CX2: Neil Cohen | CY2: Jennifer Sheldon | CZ2: Karthick
A3: Profit | B3: 9 | C3: 4 | D3: 89 | E3: 182 | F3: -19 | G3: 15 | H3: 88 | I3: -25 | J3: 26 | K3: 4 | L3: 40 | M3: 255 | N3: -14 | O3: 9 | P3: 195 | Q3: 30 | R3: -1 | S3: 10 | T3: 432 | U3: 297 | V3: 71 | W3: 17 | X3: 241 | Y3: 216 | Z3: -55 | AA3: 23 | AB3: -25 | AC3: 89 | AD3: 79 | AE3: 16 | AF3: 9 | AG3: 195 | AH3: -21 | AI3: 4 | AJ3: 2 | AK3: 2 | AL3: 9 | AM3: 2 | AN3: 1 | AO3: 30 | AP3: 10 | AQ3: 14 | AR3: 2 | AS3: 127 | AT3: 89 | AU3: -99 | AV3: 15 | AW3: 165 | AX3: -21 | AY3: 35 | AZ3: 20 | BA3: 11 | BB3: 255 | BC3: -25 | BD3: 30 | BE3: -6 | BF3: 195 | BG3: -31 | BH3: 17 | BI3: 2 | BJ3: 24 | BK3: 10 | BL3: 15 | BM3: 3 | BN3: 17 | BO3: 4 | BP3: -25 | BQ3: -21 | BR3: 9 | BS3: 24 | BT3: 54 | BU3: 89 | BV3: -99 | BW3: 182 | BX3: 15 | BY3: 2 | BZ3: 35 | CA3: 2 | CB3: 9 | CC3: 1 | CD3: -33 | CE3: 2 | CF3: 255 | CG3: 165 | CH3: 1417 | CI3: 9 | CJ3: 9 | CK3: 30 | CL3: 195 | CM3: 58 | CN3: 30 | CO3: -1 | CP3: 2 | CQ3: 35 | CR3: 10 | CS3: 17 | CT3: 2 | CU3: 3 | CV3: 28 | CW3: -55 | CX3: 23 | CY3: 4 | CZ3: 8
A4: Sales | B4: 33 | C4: 11 | D4: 281 | E4: 388 | F4: 56 | G4: 42 | H4: 258 | I4: 58 | J4: 174 | K4: 15 | L4: 94 | M4: 601 | N4: 753 | O4: 19 | P4: 1243 | Q4: 88 | R4: 3 | S4: 20 | T4: 1843 | U4: 712 | V4: 198 | W4: 38 | X4: 830 | Y4: 1091 | Z4: 868 | AA4: 74 | AB4: 58 | AC4: 281 | AD4: 402 | AE4: 159 | AF4: 115 | AG4: 1243 | AH4: 40 | AI4: 9 | AJ4: 7 | AK4: 7 | AL4: 24 | AM4: 16 | AN4: 2 | AO4: 74 | AP4: 22 | AQ4: 79 | AR4: 16 | AS4: 1039 | AT4: 281 | AU4: 72 | AV4: 42 | AW4: 541 | AX4: 40 | AY4: 99 | AZ4: 64 | BA4: 137 | BB4: 601 | BC4: 58 | BD4: 88 | BE4: 14 | BF4: 1243 | BG4: 83 | BH4: 38 | BI4: 7 | BJ4: 54 | BK4: 22 | BL4: 55 | BM4: 6 | BN4: 38 | BO4: 10 | BP4: 58 | BQ4: 40 | BR4: 19 | BS4: 258 | BT4: 725 | BU4: 281 | BV4: 72 | BW4: 388 | BX4: 42 | BY4: 7 | BZ4: 99 | CA4: 41 | CB4: 68 | CC4: 3 | CD4: 30 | CE4: 7 | CF4: 601 | CG4: 541 | CH4: 5607 | CI4: 19 | CJ4: 19 | CK4: 88 | CL4: 1243 | CM4: 126 | CN4: 88 | CO4: 3 | CP4: 16 | CQ4: 99 | CR4: 679 | CS4: 38 | CT4: 7 | CU4: 6 | CV4: 79 | CW4: 868 | CX4: 74 | CY4: 10 | CZ4: 18

Sheet Sheet2
A1: Order ID | B1: Customer Name | C1: Profit
A2: CA-2019-100867 | B2: =VLOOKUP(A2,data,2,FALSE) -> #NAME? | C2: =_xlfn.IFNA(VLOOKUP(A2,data,3,FALSE),"Order id is not available") -> #NAME?
A3: CA-2019-126634 | B3: =VLOOKUP(A3,data,2,FALSE) -> #NAME? | C3: =_xlfn.IFNA(VLOOKUP(A3,data,3,FALSE),"Order id is not available") -> #NAME?
A4: CA-2019-152443 | B4: =VLOOKUP(A4,data,2,FALSE) -> #NAME? | C4: =_xlfn.IFNA(VLOOKUP(A4,data,3,FALSE),"Order id is not available") -> #NAME?
A5: CA-2019-160325 | B5: =VLOOKUP(A5,data,2,FALSE) -> #NAME? | C5: =_xlfn.IFNA(VLOOKUP(A5,data,3,FALSE),"Order id is not available") -> #NAME?
A6: CA-2020-145154 | B6: =VLOOKUP(A6,data,2,FALSE) -> #NAME? | C6: =_xlfn.IFNA(VLOOKUP(A6,data,3,FALSE),"Order id is not available") -> #NAME?
A7: CA-2020-111111 | B7: =VLOOKUP(A7,data,2,FALSE) -> #NAME? | C7: =_xlfn.IFNA(VLOOKUP(A7,data,3,FALSE),"Order id is not available") -> #NAME?
A8: CA-2020-152681 | B8: =VLOOKUP(A8,data,2,FALSE) -> #NAME? | C8: =_xlfn.IFNA(VLOOKUP(A8,data,3,FALSE),"Order id is not available") -> #NAME?
A15: Order ID | B15: Customer Name | C15: Profit
A16: CA-2019-100867 | B16: =HLOOKUP(A16,hlookup!$A$1:$CZ$4,2,FALSE) -> Eugene Hildebrand | C16: =VLOOKUP(A16,Sheet1!$A$2:$D$104,MATCH(Sheet1!C1,Sheet1!A1:D1,0),0) -> 9
A17: CA-2019-126634 | B17: =HLOOKUP(A17,hlookup!$A$1:$CZ$4,2,FALSE) -> Alan Barnes | C17: =VLOOKUP(A17,Sheet1!$A$2:$D$104,MATCH(Sheet1!C2,Sheet1!A2:D2,0),0) -> 40
A18: CA-2019-152443 | B18: =HLOOKUP(A18,hlookup!$A$1:$CZ$4,2,FALSE) -> Frank Gastineau | C18: =VLOOKUP(A18,Sheet1!$A$2:$D$104,MATCH(Sheet1!C3,Sheet1!A3:D3,0),0) -> 297
A19: CA-2019-160325 | B19: =HLOOKUP(A19,hlookup!$A$1:$CZ$4,2,FALSE) -> Bart Pistole | C19: =VLOOKUP(A19,Sheet1!$A$2:$D$104,MATCH(Sheet1!C4,Sheet1!A4:D4,0),0) -> 241
A20: CA-2020-145154 | B20: =HLOOKUP(A20,hlookup!$A$1:$CZ$4,2,FALSE) -> Michael Knudson | C20: =VLOOKUP(A20,Sheet1!$A$2:$D$104,MATCH(Sheet1!C5,Sheet1!A5:D5,0),0) -> -21
A21: CA-2020-111111 | B21: =HLOOKUP(A21,hlookup!$A$1:$CZ$4,2,FALSE) -> Karthick | C21: =VLOOKUP(A21,Sheet1!$A$2:$D$104,MATCH(Sheet1!C6,Sheet1!A6:D6,0),0) -> 8
A22: CA-2020-152681 | B22: =HLOOKUP(A22,hlookup!$A$1:$CZ$4,2,FALSE) -> Scott Cohen | C22: =VLOOKUP(A22,Sheet1!$A$2:$D$104,MATCH(Sheet1!C7,Sheet1!A7:D7,0),0) -> 2

Sheet app_match
C1: Selling Price | E1: TAX Rate
C2: Lower End | D2: Higher End | E2: VAT
C3: 1001 | D3: 2000 | E3: 0.05
C4: 2001 | D4: 5000 | E4: 0.1
C5: 5001 | D5: 10000 | E5: 0.2
C6: 10001 | D6: above | E6: 0.3
C12: Selling Price | D12: Tax
C13: 1500 | D13: =VLOOKUP(C13,C3:E6,3,TRUE) -> 0.05
C14: 2500 | D14: =VLOOKUP(C14,C4:E7,3,TRUE) -> 0.1
C15: 20000 | D15: =VLOOKUP(C15,C5:E8,3,TRUE) -> 0.3
C16: 10000 | D16: =VLOOKUP(C16,C6:E9,3,TRUE) -> #N/A
